zertoapl/__init__.py
zertoapl/vpg.py
zertoapl/vra.py
zertoapl/zerto_auth.py
zertoapl/zvm.py
zertoapl-0.0.4.dist-info/LICENSE
zertoapl-0.0.4.dist-info/METADATA
zertoapl-0.0.4.dist-info/WHEEL
zertoapl-0.0.4.dist-info/top_level.txt
zertoapl-0.0.4.dist-info/RECORD
