Metadata-Version: 2.1
Name: zertoapl
Version: 0.0.4
Summary: Zerto Automation API Library
Home-page: https://github.com/pilotschenck/pyzerto-unofficial
Author: Alex Schenck and Shaun Finn
Author-email: linuxbeak@gmail.com, shaun_ryan_finn@yahoo.com
License: UNKNOWN
Platform: UNKNOWN
Classifier: Programming Language :: Python :: 3
Classifier: License :: OSI Approved :: Apache Software License
Classifier: Operating System :: OS Independent
Requires-Python: >=3.8
Requires-Dist: requests (>=2.25.0)
